{
  "": null,
  "32980": "GM",
  "37977": "Moog",
  "863577": "ACDelco/GM",
  "863578": "Motorcraft/Ford",
  "863579": "US Star",
  "864638": "Castrol",
  "864639": "Tornado",
  "864640": "Isuzu",
  "864641": "Peugeot",
  "864642": "Hyundai",
  "864643": "Nissan",
  "864644": "Mitsubishi",
  "864645": "Hino",
  "864646": "Toyota",
  "864647": "Daihatsu",
  "864665": "Motorcraft",
  "864666": "Shell",
  "864667": "Acdelco",
  "864668": "Mobil1",
  "864854": "Honda",
  "864855": "Kia",
  "864856": "Mazda",
  "864857": "Mopar",
  "864891": "TYC",
  "864892": "Depo",
  "864893": "Mobis",
  "864898": "Avon",
  "864899": "Delux",
  "865161": "DENSO",
  "865162": "TAIWAN"
}
